dotnet_deptree/__init__.py
dotnet_deptree/cli.py
dotnet_deptree/dag/dag.py
dotnet_deptree/dag/path_based_dependency_tree.py
dotnet_deptree/deptree_generator.py
dotnet_deptree/dotnet.py
dotnet_deptree/utils/colors.py
dotnet_deptree-0.1.4.dist-info/LICENSE
dotnet_deptree-0.1.4.dist-info/METADATA
dotnet_deptree-0.1.4.dist-info/WHEEL
dotnet_deptree-0.1.4.dist-info/entry_points.txt
dotnet_deptree-0.1.4.dist-info/RECORD
