Metadata-Version: 2.1
Name: dotnet-deptree
Version: 0.1.4
Summary: Generate dependency tree visualizations for .NET projects
Home-page: https://github.com/jicruz96/dotnet-deptree
License: MIT
Keywords: .NET,graphviz,dependencies,visualization,dotnet,deptree
Author: J.I. Cruz
Author-email: israel.jose.pr@gmail.com
Requires-Python: >=3.11,<4.0
Classifier: Development Status :: 3 - Alpha
Classifier: Environment :: Console
Classifier: Intended Audience :: Developers
Classifier: License :: OSI Approved :: MIT License
Classifier: Programming Language :: C#
Classifier: Programming Language :: Python :: 3
Classifier: Programming Language :: Python :: 3.11
Classifier: Programming Language :: Python :: 3.12
Classifier: Topic :: Documentation
Classifier: Topic :: Software Development :: Build Tools
Classifier: Topic :: Software Development :: Documentation
Requires-Dist: graphviz (>=0.20.1,<0.21.0)
Requires-Dist: xmltodict (>=0.13.0,<0.14.0)
Project-URL: Repository, https://github.com/jicruz96/dotnet-deptree
